liebres/__init__.py
liebres/_version.py
liebres/dataframes/__init__.py
liebres/dataframes/abc.py
liebres/dataframes/sqlite.py
tests/__init__.py
tests/test_dataframes/__init__.py
tests/test_dataframes/test_sqlite.py
liebres-0.0.1.dist-info/LICENSE
liebres-0.0.1.dist-info/METADATA
liebres-0.0.1.dist-info/WHEEL
liebres-0.0.1.dist-info/top_level.txt
liebres-0.0.1.dist-info/RECORD
