Metadata-Version: 2.1
Name: liebres
Version: 0.0.1
Summary: Flexible and powerful data analysis / manipulation library for Python on top of SQL, providing labeled data structures.
Home-page: https://github.com/garciparedes/liebres
Author: Sergio García Prado
Author-email: sergio@garciparedes.me
License: UNKNOWN
Platform: UNKNOWN
Requires-Dist: cached-property (>=1.5.1)
Provides-Extra: all
Requires-Dist: sphinx ; extra == 'all'
Requires-Dist: sphinx-rtd-theme ; extra == 'all'
Requires-Dist: sphinxcontrib-apidoc ; extra == 'all'
Requires-Dist: coverage ; extra == 'all'
Requires-Dist: codecov ; extra == 'all'
Requires-Dist: flake8 ; extra == 'all'
Requires-Dist: mypy ; extra == 'all'
Requires-Dist: coloredlogs ; extra == 'all'
Provides-Extra: docs
Requires-Dist: sphinx ; extra == 'docs'
Requires-Dist: sphinx-rtd-theme ; extra == 'docs'
Requires-Dist: sphinxcontrib-apidoc ; extra == 'docs'
Provides-Extra: logs
Requires-Dist: coloredlogs ; extra == 'logs'
Provides-Extra: syntax
Requires-Dist: flake8 ; extra == 'syntax'
Requires-Dist: mypy ; extra == 'syntax'
Provides-Extra: tests
Requires-Dist: coverage ; extra == 'tests'
Requires-Dist: codecov ; extra == 'tests'
